[
  {
    "ID": "m00_10_00_00",
    "Name": "Garage",
    "Tags": [
      ""
    ]
  },
  {
    "ID": "m00_12_00_00",
    "Name": "",
    "Tags": [
      ""
    ]
  },
  {
    "ID": "m00_90_00_00",
    "Name": "AC Test",
    "Tags": [
      ""
    ]
  },
  {
    "ID": "m01_00_30_00",
    "Name": "Mission 9100 - AC Test",
    "Tags": [
      ""
    ]
  },
  {
    "ID": "m01_00_50_00",
    "Name": "",
    "Tags": [
      ""
    ]
  },
  {
    "ID": "m01_00_60_00",
    "Name": "",
    "Tags": [
      ""
    ]
  },
  {
    "ID": "m01_00_70_00",
    "Name": "Mission 4020 - Watchpoint Alpha - Underground Exploration - Depth 3",
    "Tags": [
      ""
    ]
  },
  {
    "ID": "m01_00_80_00",
    "Name": "Mission 4100 - Watchpoint Alpha - MIA",
    "Tags": [
      ""
    ]
  },
  {
    "ID": "m01_01_00_00",
    "Name": "Mission 5110 - Xylem Control Block - Regain Control of the Xylem",
    "Tags": [
      ""
    ]
  },
  {
    "ID": "m01_01_10_00",
    "Name": "Mission 2010 - Grid 135 - Illegal Entry",
    "Tags": [
      ""
    ]
  },
  {
    "ID": "m01_01_30_00",
    "Name": "Mission 5040 - Xylem Upper Districts - Breach the Karman Line",
    "Tags": [
      ""
    ]
  },
  {
    "ID": "m01_01_40_00",
    "Name": "Mission 2080 - Bona Dea Dunes - Destroy the Weaponized Mining Ship",
    "Tags": [
      ""
    ]
  },
  {
    "ID": "m01_01_50_00",
    "Name": "Mission 2020 and 2025 - Gallia Dam Complex - Attack the Dam Complex",
    "Tags": [
      ""
    ]
  },
  {
    "ID": "m01_01_60_00",
    "Name": "",
    "Tags": [
      ""
    ]
  },
  {
    "ID": "m01_01_80_00",
    "Name": "Mission 2240 - Gallia Dam Complex - Defend the Dam Complex",
    "Tags": [
      ""
    ]
  },
  {
    "ID": "m01_02_30_00",
    "Name": "Mission 3420 - Engebret Tunnel - Tunnel Sabotage",
    "Tags": [
      ""
    ]
  },
  {
    "ID": "m01_02_50_00",
    "Name": "Mission 2030 - The Wall - Operation Wallclimber",
    "Tags": [
      ""
    ]
  },
  {
    "ID": "m01_02_60_00",
    "Name": "Mission 2050 and 2055 - Watchpoint Delta - Attack the Watchpoint",
    "Tags": [
      ""
    ]
  },
  {
    "ID": "m01_02_80_00",
    "Name": "Mission 2140 - Contaminated City - Prisoner Rescue",
    "Tags": [
      ""
    ]
  },
  {
    "ID": "m01_03_20_00",
    "Name": "Mission 3430 - Old Bertram Spaceport Environs - Destroy the Special Forces Craft",
    "Tags": [
      ""
    ]
  },
  {
    "ID": "m01_03_50_00",
    "Name": "Mission 2100 - The Wall - Retrieve Combat Logs",
    "Tags": [
      ""
    ]
  },
  {
    "ID": "m01_03_60_00",
    "Name": "Mission 2060 - BAWS Arsenal No. 2 - Investigate BAWS Arsenal No. 2",
    "Tags": [
      ""
    ]
  },
  {
    "ID": "m01_03_70_00",
    "Name": "Mission 2120 - Grid 086 - Infiltrate Grid 086",
    "Tags": [
      ""
    ]
  },
  {
    "ID": "m01_03_90_00",
    "Name": "Mission 2230 - Grid 086 - Stop the Secret Data Breach",
    "Tags": [
      ""
    ]
  },
  {
    "ID": "m01_04_00_00",
    "Name": "Mission 3030 - Jorgen Refueling Base - Attack the Refueling Base",
    "Tags": [
      ""
    ]
  },
  {
    "ID": "m01_04_10_00",
    "Name": "Mission 2211 - Jorgen Refueling Base - Coral Export Denial",
    "Tags": [
      ""
    ]
  },
  {
    "ID": "m01_04_20_00",
    "Name": "Mission 3043 - Old Bertram Spaceport - Attack the Old Spaceport",
    "Tags": [
      ""
    ]
  },
  {
    "ID": "m01_04_60_00",
    "Name": "Mission 2170 - The Wall - Eliminate V.VII",
    "Tags": [
      ""
    ]
  },
  {
    "ID": "m01_04_70_00",
    "Name": "Mission 5100 and 5105 - Xylem, the Floating City - Survey the Uninhabited Floating City",
    "Tags": [
      ""
    ]
  },
  {
    "ID": "m01_04_80_00",
    "Name": "Mission 5010 - Xylem, the Floating City - Take the Uninhabited Floating City",
    "Tags": [
      ""
    ]
  },
  {
    "ID": "m01_04_90_00",
    "Name": "Mission 5030 - Xylem Drive Block - Destroy the Drive Block",
    "Tags": [
      ""
    ]
  },
  {
    "ID": "m01_05_30_00",
    "Name": "Mission 5020 - Xylem Upper Districts - Intercept the Corporate Forces",
    "Tags": [
      ""
    ]
  },
  {
    "ID": "m01_06_00_00",
    "Name": "Mission 9001 - Garage - Unknown",
    "Tags": [
      ""
    ]
  },
  {
    "ID": "m01_06_10_00",
    "Name": "Mission 4000 - Watchpoint Alpha - Underground Exploration - Depth 1",
    "Tags": [
      ""
    ]
  },
  {
    "ID": "m01_06_20_00",
    "Name": "Mission 4010 and 4015 - Watchpoint Alpha - Underground Exploration - Depth 2",
    "Tags": [
      ""
    ]
  },
  {
    "ID": "m01_06_30_00",
    "Name": "Mission 4021 and 4026 - Watchpoint Alpha - Unknown Territory Survey",
    "Tags": [
      ""
    ]
  },
  {
    "ID": "m01_06_40_00",
    "Name": "Mission 4030 and 4035 - Institute City - Reach the Coral Convergence",
    "Tags": [
      ""
    ]
  },
  {
    "ID": "m01_06_60_00",
    "Name": "Mission 3500 - Engebret Tunnel - Historic Data Recovery",
    "Tags": [
      ""
    ]
  },
  {
    "ID": "m01_06_80_00",
    "Name": "Mission 3230 - Unobservable Area - Destroy the Ice Worm",
    "Tags": [
      ""
    ]
  },
  {
    "ID": "m01_06_90_00",
    "Name": "",
    "Tags": [
      ""
    ]
  },
  {
    "ID": "m01_07_20_00",
    "Name": "Mission 3320 - Grid 012 - Eliminate 'Honest' Brute",
    "Tags": [
      ""
    ]
  },
  {
    "ID": "m01_07_50_00",
    "Name": "Mission 6000 - LOC Station 31 - Shut Down the Closure Satellites",
    "Tags": [
      ""
    ]
  },
  {
    "ID": "m01_07_60_00",
    "Name": "Mission 6010 - Xylem Upper Districts - Bring Down the Xylem",
    "Tags": [
      ""
    ]
  },
  {
    "ID": "m01_07_70_00",
    "Name": "Mission 9200 - AC Test - Beginner Training 1: Basic Controls",
    "Tags": [
      ""
    ]
  },
  {
    "ID": "m01_07_80_00",
    "Name": "Mission 6020 - LOC Station 31 - Coral Release",
    "Tags": [
      ""
    ]
  },
  {
    "ID": "m01_08_10_00",
    "Name": "Mission 2200 - BAWS Arsenal No. 2 - Obstruct the Mandatory Inspection",
    "Tags": [
      ""
    ]
  },
  {
    "ID": "m01_08_40_00",
    "Name": "Mission 2220 - Watchpoint Delta - Heavy Missile Launch Support",
    "Tags": [
      ""
    ]
  },
  {
    "ID": "m01_08_50_00",
    "Name": "Mission 2180 - Grid 086 - Ocean Crossing",
    "Tags": [
      ""
    ]
  },
  {
    "ID": "m01_08_60_00",
    "Name": "Mission 4200 - Institute City - Escape",
    "Tags": [
      ""
    ]
  },
  {
    "ID": "m01_08_70_00",
    "Name": "Mission 2250 - Bona Dea Dunes - Escort the Weaponized Mining Ship",
    "Tags": [
      ""
    ]
  },
  {
    "ID": "m01_08_80_00",
    "Name": "Mission 5050 - Xylem Upper Districts - Eliminate 'Cinder' Carla",
    "Tags": [
      ""
    ]
  },
  {
    "ID": "m01_08_90_00",
    "Name": "Mission 3011 - Hjalmar Mine - Steal the Survey Data",
    "Tags": [
      ""
    ]
  },
  {
    "ID": "m01_09_00_00",
    "Name": "Mission 4110 - Watchpoint Alpha - Ambush the Vespers",
    "Tags": [
      ""
    ]
  },
  {
    "ID": "m01_09_10_00",
    "Name": "Mission 9201 - AC Test - Beginner Training 2: Combat Fundamentals",
    "Tags": [
      ""
    ]
  },
  {
    "ID": "m01_10_00_00",
    "Name": "Mission 7900 - Contaminated City - Destroy the Transport Helicopters",
    "Tags": [
      ""
    ]
  },
  {
    "ID": "m01_10_20_00",
    "Name": "Mission 7910 - Hjalmar Mine - Prevent Corporate Salvage of New Tech",
    "Tags": [
      ""
    ]
  },
  {
    "ID": "m01_10_40_00",
    "Name": "Mission 7920 - Grid 135 - Grid 135 Cleanup",
    "Tags": [
      ""
    ]
  },
  {
    "ID": "m01_10_60_00",
    "Name": "Mission 7960 - Grid 086 - Eliminate the Doser Faction",
    "Tags": [
      ""
    ]
  },
  {
    "ID": "m01_10_70_00",
    "Name": "Mission 7940 - Watchpoint Alpha - Eliminate V.III",
    "Tags": [
      ""
    ]
  },
  {
    "ID": "m01_10_90_00",
    "Name": "Mission 7930 - Watchpoint Alpha - Intercept the Redguns",
    "Tags": [
      ""
    ]
  },
  {
    "ID": "m01_11_00_00",
    "Name": "Mission 7950 - Old Bertram Spaceport - Defend the Old Spaceport",
    "Tags": [
      ""
    ]
  },
  {
    "ID": "m01_11_30_00",
    "Name": "Mission 9202 - AC Test - Intermediate Support 1: Assembling an AC",
    "Tags": [
      ""
    ]
  },
  {
    "ID": "m01_11_40_00",
    "Name": "Mission 9203 - AC Test - Intermediate Support 2: Reverse-Jointed ACs",
    "Tags": [
      ""
    ]
  },
  {
    "ID": "m01_11_60_00",
    "Name": "Mission 7970 - Contaminated City - Destroy Artillery Installations",
    "Tags": [
      ""
    ]
  },
  {
    "ID": "m01_11_70_00",
    "Name": "Mission 7980 - Contaminated City - Destroy the Tester AC",
    "Tags": [
      ""
    ]
  },
  {
    "ID": "m01_12_00_00",
    "Name": "Mission 9204 - AC Test - Intermediate Support 3: Tetrapod ACs",
    "Tags": [
      ""
    ]
  },
  {
    "ID": "m01_12_10_00",
    "Name": "Mission 9205 - AC Test - Intermediate Support 4: Tank ACs",
    "Tags": [
      ""
    ]
  },
  {
    "ID": "m01_12_20_00",
    "Name": "Mission 9206 - AC Test - Advanced Mercenary Certification",
    "Tags": [
      ""
    ]
  },
  {
    "ID": "m01_12_30_00",
    "Name": "Mission 7990 - The Wall - Eliminate the Enforcement Squads",
    "Tags": [
      ""
    ]
  },
  {
    "ID": "m01_40_00_00",
    "Name": "",
    "Tags": [
      ""
    ]
  },
  {
    "ID": "m01_40_10_00",
    "Name": "Nest 9301 - Grid 086",
    "Tags": [
      ""
    ]
  },
  {
    "ID": "m01_40_20_00",
    "Name": "Nest 9303 - Old Bertram Spaceport",
    "Tags": [
      ""
    ]
  },
  {
    "ID": "m01_40_30_00",
    "Name": "Nest 9305 - Jorgen Refueling Base",
    "Tags": [
      ""
    ]
  },
  {
    "ID": "m01_40_40_00",
    "Name": "Nest 9306 - Xylem, the Floating City",
    "Tags": [
      ""
    ]
  },
  {
    "ID": "m01_40_50_00",
    "Name": "Nest 9304 - Wall Sector",
    "Tags": [
      ""
    ]
  },
  {
    "ID": "m01_40_60_00",
    "Name": "Nest 9307 - Upper Grid 086, Outer Shell",
    "Tags": [
      ""
    ]
  },
  {
    "ID": "m01_40_70_00",
    "Name": "Nest 9308 - Grid 012",
    "Tags": [
      ""
    ]
  },
  {
    "ID": "m01_40_90_00",
    "Name": "Nest 9300 - Watchpoint Delta",
    "Tags": [
      ""
    ]
  },
  {
    "ID": "m01_41_00_00",
    "Name": "Nest 9302 - Bona Dea Dunes",
    "Tags": [
      ""
    ]
  },
  {
    "ID": "m01_50_10_00",
    "Name": "Arena 9400 - Watchpoint Delta - V.V Hawkins, Sulla, Chartreuse, 51-003 K",
    "Tags": [
      ""
    ]
  },
  {
    "ID": "m01_50_20_00",
    "Name": "Arena 9401 - Grid 086 - 'Cinder' Carla",
    "Tags": [
      ""
    ]
  },
  {
    "ID": "m01_50_30_00",
    "Name": "Arena 9402 - Bona Dea Dunes - G6 Red, G4 Volta, 51-011 AL",
    "Tags": [
      ""
    ]
  },
  {
    "ID": "m01_50_40_00",
    "Name": "Arena 9403 - Contaminated City - Index Dunham, Ring Freddie, 51-012 AL",
    "Tags": [
      ""
    ]
  },
  {
    "ID": "m01_50_50_00",
    "Name": "Arena 9404 - The Wall - Nosaac, G5 Iguazu, 51-014 BE",
    "Tags": [
      ""
    ]
  },
  {
    "ID": "m01_50_60_00",
    "Name": "Arena 9405 - Jorgen Refueling Base - Coldcall, G2 Nile, 51-013 BE",
    "Tags": [
      ""
    ]
  },
  {
    "ID": "m01_50_70_00",
    "Name": "Arena 9406 - Grid 086 - 'Chatty' Stick",
    "Tags": [
      ""
    ]
  },
  {
    "ID": "m01_50_80_00",
    "Name": "Arena 9407 - Old Bertram Spaceport Environs - Unused",
    "Tags": [
      ""
    ]
  },
  {
    "ID": "m01_50_90_00",
    "Name": "Arena 9408 - AC Test - 'Invincible' Rummy, G3 Wu Huahai, V.III O'Keeffe, King",
    "Tags": [
      ""
    ]
  },
  {
    "ID": "m01_51_00_00",
    "Name": "Arena 9409 - AC Test - V.VII Swinburne, Middle Flatwell, Thumb Dolmayan, G1 Michigan, 51-001 K",
    "Tags": [
      ""
    ]
  },
  {
    "ID": "m01_51_10_00",
    "Name": "Arena 9410 - AC Test - V.I Freud, 51-016 GA, 51-101 R, 51-201 W",
    "Tags": [
      ""
    ]
  },
  {
    "ID": "m01_51_20_00",
    "Name": "Arena 9411 - AC Test - Ayre",
    "Tags": [
      ""
    ]
  },
  {
    "ID": "m01_51_30_00",
    "Name": "Arena 9412 - BAWS Arsenal No. 2 - V.VI Maeterlinck, V.VIII Pater, 51-002 K",
    "Tags": [
      ""
    ]
  },
  {
    "ID": "m01_51_40_00",
    "Name": "Arena 9413 - Grid 012 - 'Honest' Brute, 51-015 GA",
    "Tags": [
      ""
    ]
  },
  {
    "ID": "m01_51_50_00",
    "Name": "Arena 9414 - Old Bertram Spaceport - V.II Snail",
    "Tags": [
      ""
    ]
  },
  {
    "ID": "m01_51_60_00",
    "Name": "Arena 9415 - Gallia Dam Complex - Little Ziyi, Rokumonsen",
    "Tags": [
      ""
    ]
  },
  {
    "ID": "m01_51_70_00",
    "Name": "Arena 9416 - Xylem, the Floating City - V.IV Rusty",
    "Tags": [
      ""
    ]
  },
  {
    "ID": "m03_20_00_00",
    "Name": "Central Ice Field - Hjalmar Mine",
    "Tags": [
      ""
    ]
  },
  {
    "ID": "m03_30_00_00",
    "Name": "Central Ice Field - Jorgen Refueling Base",
    "Tags": [
      ""
    ]
  },
  {
    "ID": "m03_40_00_00",
    "Name": "Central Ice Field - Old Bertram Spaceport and Engebret Tunnel",
    "Tags": [
      ""
    ]
  },
  {
    "ID": "m03_60_00_00",
    "Name": "Central Ice Field - Old Bertram Spaceport Environs and Unobservable Area",
    "Tags": [
      ""
    ]
  },
  {
    "ID": "m10_00_00_00",
    "Name": "Southern Belius - Grid 135",
    "Tags": [
      ""
    ]
  },
  {
    "ID": "m10_01_00_00",
    "Name": "",
    "Tags": [
      ""
    ]
  },
  {
    "ID": "m10_10_00_00",
    "Name": "Western Belius - Grid 086",
    "Tags": [
      ""
    ]
  },
  {
    "ID": "m10_20_00_00",
    "Name": "Contaminated Zone - Grid 012",
    "Tags": [
      ""
    ]
  },
  {
    "ID": "m20_00_00_00",
    "Name": "Alean Ocean - Xylem, the Floating City",
    "Tags": [
      ""
    ]
  },
  {
    "ID": "m20_20_00_00",
    "Name": "Atmosphere - Xylem Upper Districts",
    "Tags": [
      ""
    ]
  },
  {
    "ID": "m20_30_00_00",
    "Name": "Amtosphere - Xylem Drive Block and Xylem Control Block",
    "Tags": [
      ""
    ]
  },
  {
    "ID": "m30_00_00_00",
    "Name": "Atmosphere - LOC Station 31",
    "Tags": [
      ""
    ]
  },
  {
    "ID": "m41_00_00_00",
    "Name": "Watchpoint Alpha",
    "Tags": [
      ""
    ]
  },
  {
    "ID": "m41_10_00_00",
    "Name": "Institute City",
    "Tags": [
      ""
    ]
  },
  {
    "ID": "m50_00_00_00",
    "Name": "Southern Belius - Contaminated City",
    "Tags": [
      ""
    ]
  },
  {
    "ID": "m50_10_00_00",
    "Name": "Southern Belius - Gallia Dam Complex",
    "Tags": [
      ""
    ]
  },
  {
    "ID": "m50_30_00_00",
    "Name": "Central Belius - The Wall",
    "Tags": [
      ""
    ]
  },
  {
    "ID": "m50_40_00_00",
    "Name": "Northern Belius - Watchpoint Delta",
    "Tags": [
      ""
    ]
  },
  {
    "ID": "m50_50_00_00",
    "Name": "Northern Belius - BAWS Arsenal No. 2",
    "Tags": [
      ""
    ]
  },
  {
    "ID": "m50_60_00_00",
    "Name": "Western Belius - Bona Dea Dunes",
    "Tags": [
      ""
    ]
  }
]