<?xml version="1.0" encoding="UTF-8"?>
<PARAMMETA XmlVersion="0">
    <Field>
        <modelId />
        <animId />
        <commonId />
        <moveId />
        <npcStatusId />
        <groupType  Enum="CHR_GROUP_TYPE"/>
        <categoryType  Enum="CHR_CATEGORY_TYPE"/>
        <materialType  Enum="MATERIAL_TYPE_ENUM"/>
        <visualType  Enum="CHR_VISUAL_TYPE"/>
        <multiplayParamId />
        <respawnNum />
        <isUndead  IsBool=""/>
        <isRunaway  IsBool=""/>
        <hitPoint />
        <staminaPoint />
        <staminaRecoveryValue />
        <staminaLoanMin />
        <staminaLoanMax />
        <staminaCostMoveBase />
        <deadType  Refs="DeadTypeParam"/>
        <deadType02  Refs="DeadTypeParam"/>
        <defaultEquipWeapon  Enum="ENEMY_WEAPON_TYPE"/>
        <equipWeaponAId00 />
        <equipWeaponAId01 />
        <equipWeaponAId02 />
        <equipWeaponAId03 />
        <equipWeaponAId04 />
        <equipWeaponAId05 />
        <equipAccessory01 />
        <equipAccessory02 />
        <equipAccessory03 />
        <equipAccessory04 />
        <equipAccessory05 />
        <roundDamageCategory Refs="ChrRoundDamageParam" />
        <guardPassiveLevelType  Enum="GUARD_PASSIVE_LEVEL_TYPE"/>
        <parryType  Enum="PARRY_TYPES"/>
        <spellParrySfxId />
        <shieldMaterialType  Enum="MATERIAL_TYPE_ENUM"/>
        <shieldReceiveValue />
        <shieldDefenseValue />
        <shieldMagicDefenseValue />
        <shieldMiracleDefenseValue />
        <shieldPyromancyDefenseValue />
        <shieldDarkMagicDefenseValue />
        <shieldPoisonDefenseValue />
        <shieldBleedingDefenseValue />
        <shieldDestructionDefenseValue />
        <shieldCurseDefenseValue />
        <armorDefenseValue />
        <armorMagicDefenseValue />
        <armorMiracleDefenseValue />
        <armorPyromancyDefenseValue />
        <armorDarkMagicDefenseValue />
        <armorPoisonDefenseValue />
        <armorBleedingDefenseValue />
        <armorDestructionDefenseValue />
        <armorCurseDefenseValue />
        <armorMaterialType  Enum="MATERIAL_TYPE_ENUM"/>
        <armorToughValue />
        <armorStunBaseValue />
        <armorStunRecoveryRate />
        <dropSoulValue />
        <dropType  Enum="CHR_ITEM_DROP_TYPE"/>
        <damageAdjustRate />
        <damageAdjustRatePlayer />
        <damageAdjustRateEnemy />
        <damageAdjustRateNeutral />
        <damageAdjustRateHitObj />
        <residentDamageId1 />
        <residentDamageId2 />
        <residentDamageId3 />
        <stunDisableFlag  IsBool=""/>
        <isPartsGuardDamage  IsBool=""/>
        <isPartsGuardBullet  IsBool=""/>
        <isPartsGuardSpellParry  IsBool=""/>
        <stunMaxValue />
        <stunRecoverValue />
        <changeStunMaxValue />
        <changeStunRecoverValue />
        <fadeInTime />
        <generateSfx Refs="ChrFullBodySfxParam" />
        <partsGuardSpellParryAngle />
        <poiseValue />
        <poiseRecoveryValue />
        <changePoiseValue />
        <changePoiseRecoveryValue />
        <overKillRate />
        <decLimitTime />
        <isDisallowMultiTarget  IsBool=""/>
        <isHollow  IsBool=""/>
        <isClothHitMap  IsBool=""/>
        <roundDropSoulCategory  Refs="ChrRoundDropSoulParam"/>
        <itemLotId  Refs="ItemLotParam2_Chr"/>
        <itemLotIdForGuest  Refs="ItemLotParam2_Chr"/>
        <guardDelay />
        <hitPoint02 />
        <hitPoint03 />
        <hitPoint04 />
        <hitPoint05 />
        <hitPoint06 />
        <hitPoint07 />
        <hitPoint08 />
        <nameTextId />
        <bStrongDrop  IsBool=""/>
        <bThrowableByEnemy  IsBool=""/>
        <bBulletAllDelete  IsBool=""/>
        <padding />
        <effectID />
    </Field>
</PARAMMETA>
