<?xml version="1.0" encoding="utf-8"?>
<PARAMDEF XmlVersion="3">
  <ParamType>ENEMY_COMMON_ST</ParamType>
  <DataVersion>1</DataVersion>
  <BigEndian>True</BigEndian>
  <Unicode>False</Unicode>
  <FormatVersion>104</FormatVersion>
  <Fields>
    <Field Def="fixstr BehaviorName[32]">
      <DisplayName>挙動名</DisplayName>
      <DisplayFormat />
      <EditFlags>None</EditFlags>
      <Minimum>0</Minimum>
      <Maximum>0</Maximum>
      <Increment>0</Increment>
      <SortID>1</SortID>
    </Field>
    <Field Def="u32 FcsID">
      <Maximum>9999</Maximum>
      <SortID>2</SortID>
    </Field>
    <Field Def="u32 GraphicsParamId">
      <DisplayName>グラフィッカー用パラメータID</DisplayName>
      <Description>グラフィッカー用パラメータID</Description>
      <Maximum>10000</Maximum>
      <SortID>3</SortID>
    </Field>
    <Field Def="u32 BasicParamId">
      <DisplayName>基本パラメータID</DisplayName>
      <Description>基本パラメータID</Description>
      <Maximum>10000</Maximum>
      <SortID>4</SortID>
    </Field>
    <Field Def="u16 PerformanceId">
      <DisplayName>パフォーマンスID</DisplayName>
      <Description>パフォーマンスID</Description>
      <Maximum>9999</Maximum>
      <SortID>5</SortID>
    </Field>
    <Field Def="u16 WeaponId_00">
      <DisplayName>武器ID_00</DisplayName>
      <Description>武器ID_00</Description>
      <Maximum>9999</Maximum>
      <SortID>6</SortID>
    </Field>
    <Field Def="u16 WeaponId_01">
      <DisplayName>武器ID_01</DisplayName>
      <Description>武器ID_01</Description>
      <Maximum>9999</Maximum>
      <SortID>7</SortID>
    </Field>
    <Field Def="u16 WeaponId_02">
      <DisplayName>武器ID_02</DisplayName>
      <Description>武器ID_02</Description>
      <Maximum>9999</Maximum>
      <SortID>8</SortID>
    </Field>
    <Field Def="u16 WeaponId_03">
      <DisplayName>武器ID_03</DisplayName>
      <Description>武器ID_03</Description>
      <Maximum>9999</Maximum>
      <SortID>9</SortID>
    </Field>
    <Field Def="u16 WeaponId_04">
      <DisplayName>武器ID_04</DisplayName>
      <Description>武器ID_04</Description>
      <Maximum>9999</Maximum>
      <SortID>10</SortID>
    </Field>
    <Field Def="u16 WeaponId_05">
      <DisplayName>武器ID_05</DisplayName>
      <Description>武器ID_05</Description>
      <Maximum>9999</Maximum>
      <SortID>11</SortID>
    </Field>
    <Field Def="u16 WeaponId_06">
      <DisplayName>武器ID_06</DisplayName>
      <Description>武器ID_06</Description>
      <Maximum>9999</Maximum>
      <SortID>12</SortID>
    </Field>
    <Field Def="u16 WeaponId_07">
      <DisplayName>武器ID_07</DisplayName>
      <Description>武器ID_07</Description>
      <Maximum>9999</Maximum>
      <SortID>13</SortID>
    </Field>
    <Field Def="u16 WeaponId_08">
      <DisplayName>武器ID_08</DisplayName>
      <Description>武器ID_08</Description>
      <Maximum>9999</Maximum>
      <SortID>14</SortID>
    </Field>
    <Field Def="u16 WeaponId_09">
      <DisplayName>武器ID_09</DisplayName>
      <Description>武器ID_09</Description>
      <Maximum>9999</Maximum>
      <SortID>15</SortID>
    </Field>
    <Field Def="u16 WeaponId_10">
      <DisplayName>武器ID_10</DisplayName>
      <Description>武器ID_10</Description>
      <Maximum>9999</Maximum>
      <SortID>16</SortID>
    </Field>
    <Field Def="u16 WeaponId_11">
      <DisplayName>武器ID_11</DisplayName>
      <Description>武器ID_11</Description>
      <Maximum>9999</Maximum>
      <SortID>17</SortID>
    </Field>
    <Field Def="u16 WeaponId_12">
      <DisplayName>武器ID_12</DisplayName>
      <Description>武器ID_12</Description>
      <Maximum>9999</Maximum>
      <SortID>18</SortID>
    </Field>
    <Field Def="u16 WeaponId_13">
      <DisplayName>武器ID_13</DisplayName>
      <Description>武器ID_13</Description>
      <Maximum>9999</Maximum>
      <SortID>19</SortID>
    </Field>
    <Field Def="u16 WeaponId_14">
      <DisplayName>武器ID_14</DisplayName>
      <Description>武器ID_14</Description>
      <Maximum>9999</Maximum>
      <SortID>20</SortID>
    </Field>
    <Field Def="u16 WeaponId_15">
      <DisplayName>武器ID_15</DisplayName>
      <Description>武器ID_15</Description>
      <Maximum>9999</Maximum>
      <SortID>21</SortID>
    </Field>
    <Field Def="dummy8 Reserve5[32]">
      <DisplayName>予約</DisplayName>
      <DisplayFormat>%d</DisplayFormat>
      <EditFlags>Wrap</EditFlags>
      <Maximum>9999</Maximum>
      <Increment>1</Increment>
      <SortID>22</SortID>
    </Field>
    <Field Def="u8 BomberIniAnimID">
      <DisplayName>爆撃機初期アニメID</DisplayName>
      <Description>爆撃機初期アニメID</Description>
      <SortID>38</SortID>
    </Field>
    <Field Def="s8 ACV_AIDLC_AIRaycastYOffset">
      <DisplayName>ACVAIDLC視線ターゲットY軸オフセット[m]</DisplayName>
      <Description>ACV AIDLC AIの視線ターゲットY軸オフセット[m]。０で、従来通り、当たり形状から算出。</Description>
      <Minimum>-100</Minimum>
      <Maximum>100</Maximum>
      <SortID>39</SortID>
    </Field>
    <Field Def="s32 BossId">
      <DisplayName>ボスID</DisplayName>
      <Description>ボスID（0：ボスじゃない）</Description>
      <Minimum>0</Minimum>
      <Maximum>9999</Maximum>
      <SortID>40</SortID>
    </Field>
    <Field Def="s8 ActionScriptCommonParam">
      <DisplayName>アクションスクリプト汎用値</DisplayName>
      <Description>アクションスクリプト汎用値</Description>
      <Minimum>0</Minimum>
      <Maximum>100</Maximum>
      <SortID>41</SortID>
    </Field>
    <Field Def="u8 AutoBoostEnable">
      <DisplayName>オートブースト有効無効設定</DisplayName>
      <Enum>ON_OFF</Enum>
      <Description>オートブーストの有効無効設定</Description>
      <Maximum>1</Maximum>
      <SortID>42</SortID>
    </Field>
    <Field Def="u16 JellyFish_ExpFrame">
      <DisplayName>くらげ挙動：突進してから自爆するフレーム</DisplayName>
      <Description>くらげ挙動：突進してから自爆するフレーム</Description>
      <Maximum>10000</Maximum>
      <SortID>43</SortID>
    </Field>
    <Field Def="u8 ToriparaID">
      <DisplayName>とりあえずパラメータID</DisplayName>
      <Enum>ENEMY_TORIPARA_SUBSET_ID</Enum>
      <Description>とりあえずパラメータサブセットのサブセット毎のID。ACV2ボスのオフライン・オンライン切り替え用。</Description>
      <SortID>44</SortID>
    </Field>
    <Field Def="fixstr Reserve7[7]">
      <DisplayName>予約</DisplayName>
      <DisplayFormat />
      <EditFlags>None</EditFlags>
      <Minimum>0</Minimum>
      <Maximum>0</Maximum>
      <Increment>0</Increment>
      <SortID>50</SortID>
    </Field>
  </Fields>
</PARAMDEF>